LICENSE
MANIFEST.in
README.rst
setup.py
mitest/__init__.py
mitest/mitest.py
mitest.egg-info/PKG-INFO
mitest.egg-info/SOURCES.txt
mitest.egg-info/dependency_links.txt
mitest.egg-info/top_level.txt