Metadata-Version: 1.2
Name: mitest
Version: 0.2
Summary: mongo inspired policy test
Home-page: http://project.wyf.io/mitest
Author: WYF
Author-email: dev@wyf.io
License: MIT
Platform: UNKNOWN
Requires-Python: >=3.5
